azfuncextbase_fastapi/__init__.py
azfuncextbase_fastapi/web.py
azfuncextbase_fastapi-0.1.1.dist-info/METADATA
azfuncextbase_fastapi-0.1.1.dist-info/WHEEL
azfuncextbase_fastapi-0.1.1.dist-info/top_level.txt
azfuncextbase_fastapi-0.1.1.dist-info/RECORD
