Metadata-Version: 2.1
Name: azfuncextbase-fastapi
Version: 0.1.1
Summary: A short description of your package
Author: Your Name
Author-email: your.email@example.com
Classifier: Programming Language :: Python :: 3
Classifier: License :: OSI Approved :: MIT License
Classifier: Operating System :: OS Independent
Requires-Python: >=3.6
Requires-Dist: fastapi
Requires-Dist: azfuncextbase
Requires-Dist: uvicorn
